serial_jobs/__init__.py
serial_jobs/config.py
serial_jobs/data.py
serial_jobs/handler.py
serial_jobs/job.py
serial_jobs/main.py
serial_jobs/mqtt.py
serial_jobs/schema.py
serial_jobs/service.py
serial_jobs/specification.py
serial_jobs/task.py
serial_jobs/value.py
serial_jobs/device/__init__.py
serial_jobs/device/base.py
serial_jobs/device/bms.py
serial_jobs/device/modbus.py
serial_jobs/scripts/__init__.py
serial_jobs/scripts/convert_config.py
serial_jobs/scripts/merge_config.py
serial_jobs/scripts/run.py
serial_jobs-0.0.4.dist-info/LICENSE
serial_jobs-0.0.4.dist-info/METADATA
serial_jobs-0.0.4.dist-info/WHEEL
serial_jobs-0.0.4.dist-info/entry_points.txt
serial_jobs-0.0.4.dist-info/top_level.txt
serial_jobs-0.0.4.dist-info/RECORD
