Metadata-Version: 2.1
Name: serial-jobs
Version: 0.0.4
Summary: A tool for bidirectional communication between serial devices and MQTT brokers.
Home-page: https://github.com/pbasista/serial-jobs/
Author: Peter Bašista
Author-email: pbasista@gmail.com
License: MIT
Classifier: License :: OSI Approved :: MIT License
Classifier: Operating System :: OS Independent
Classifier: Topic :: Home Automation
Classifier: Topic :: Utilities
License-File: LICENSE
Requires-Dist: gmqtt
Requires-Dist: minimalmodbus
Requires-Dist: pyserial
Requires-Dist: strictyaml
Provides-Extra: dev
Requires-Dist: pre-commit ; extra == 'dev'
Requires-Dist: pylint ; extra == 'dev'
